chaukas/py.typed
chaukas/spec/__init__.py
chaukas/spec/client/__init__.py
chaukas/spec/client/v1/__init__.py
chaukas/spec/client/v1/client_pb2.py
chaukas/spec/client/v1/client_pb2.pyi
chaukas/spec/client/v1/client_pb2_grpc.py
chaukas/spec/common/__init__.py
chaukas/spec/common/v1/__init__.py
chaukas/spec/common/v1/events_pb2.py
chaukas/spec/common/v1/events_pb2.pyi
chaukas/spec/common/v1/events_pb2_grpc.py
chaukas/spec/common/v1/query_pb2.py
chaukas/spec/common/v1/query_pb2.pyi
chaukas/spec/common/v1/query_pb2_grpc.py
chaukas_spec_client-1.0.4.dist-info/licenses/LICENSE
chaukas_spec_client-1.0.4.dist-info/METADATA
chaukas_spec_client-1.0.4.dist-info/WHEEL
chaukas_spec_client-1.0.4.dist-info/top_level.txt
chaukas_spec_client-1.0.4.dist-info/RECORD
