Metadata-Version: 2.4
Name: chaukas-spec-client
Version: 1.0.4
Summary: Client SDK for Chaukas agent audit and explainability platform
Author: Chaukas Team
License: Apache License
Project-URL: Homepage, https://github.com/chaukasai/chaukas-spec
Project-URL: Repository, https://github.com/chaukasai/chaukas-spec
Project-URL: Issues, https://github.com/chaukasai/chaukas-spec/issues
Project-URL: Documentation, https://github.com/chaukasai/chaukas-spec#client-side-sdk-development
Classifier: Development Status :: 4 - Beta
Classifier: Intended Audience :: Developers
Classifier: License :: OSI Approved :: Apache Software License
Classifier: Programming Language :: Python :: 3
Classifier: Programming Language :: Python :: 3.9
Classifier: Programming Language :: Python :: 3.10
Classifier: Programming Language :: Python :: 3.11
Classifier: Programming Language :: Python :: 3.12
Classifier: Topic :: Software Development :: Libraries :: Python Modules
Classifier: Topic :: System :: Monitoring
Classifier: Topic :: Software Development :: Libraries :: Application Frameworks
Requires-Python: >=3.9
License-File: LICENSE
Requires-Dist: protobuf>=5.26.0
Requires-Dist: grpcio>=1.50.0
Dynamic: license-file
